ims/trashcan/__init__.py
ims/trashcan/can.py
ims/trashcan/configure.zcml
ims/trashcan/events.py
ims/trashcan/interfaces.py
ims/trashcan/permissions.py
ims/trashcan/testing.py
ims/trashcan/tool.png
ims/trashcan/trash.py
ims/trashcan/profiles/default/metadata.xml
ims/trashcan/profiles/default/registry.xml
ims/trashcan/profiles/default/toolset.xml
ims/trashcan/profiles/uninstall/toolset.xml
ims/trashcan/www/manage_trashManager.zpt
ims/trashcan/www/manage_trashedItem.zpt
ims/trashcan/www/trashManagerAdd.zpt
ims/trashcan/www/trashedItemAdd.zpt
ims.trashcan-5.1.dist-info/METADATA
ims.trashcan-5.1.dist-info/WHEEL
ims.trashcan-5.1.dist-info/entry_points.txt
ims.trashcan-5.1.dist-info/licenses/LICENSE.md
ims.trashcan-5.1.dist-info/RECORD
