Metadata-Version: 2.4
Name: ims.trashcan
Version: 5.1
Summary: Web scan settings
Project-URL: homepage, https://github.com/imsweb/ims.trashcan
Author-email: Eric Wohnlich <wohnlice@imsweb.com>
License: GPL
License-File: LICENSE.md
Classifier: Framework :: Plone :: 6.0
Classifier: Programming Language :: Python
Requires-Python: >=3.8
Requires-Dist: plone
Provides-Extra: test
Requires-Dist: formencode; extra == 'test'
Requires-Dist: plone-app-robotframework; extra == 'test'
Requires-Dist: plone-app-testing; extra == 'test'
Requires-Dist: plone-mocktestcase; extra == 'test'
Requires-Dist: pytest-plone; extra == 'test'
